[
    {
      "name": "io.netty.channel.socket.nio.NioServerSocketChannel",
      "methods": [
        { "name": "<init>", "parameterTypes": [] }
      ]
    },
    {
      "name": "sun.nio.ch.SelectorImpl",
      "fields": [
        { "name": "selectedKeys",  "allowUnsafeAccess" : true},
        { "name": "publicSelectedKeys",  "allowUnsafeAccess" : true}
      ]
    },
    {
        "name": "java.lang.management.ManagementFactory",
        "methods": [
            {
                "name": "getRuntimeMXBean",
                "parameterTypes": []
            }
        ]
    },
    {
        "name": "java.lang.management.RuntimeMXBean",
        "methods": [
            {
                "name": "getName",
                "parameterTypes": []
            }
        ]
    },
    {
        "name": "java.nio.channels.spi.SelectorProvider",
        "condition": {
            "typeReachable": "java.nio.channels.spi.SelectorProvider"
        },
        "methods": [
            {
                "name": "openSocketChannel",
                "parameterTypes": ["java.net.ProtocolFamily"]
            },
            {
                "name": "openServerSocketChannel",
                "parameterTypes": ["java.net.ProtocolFamily"]
            }
        ]
    }
]
